README.md
setup.cfg
setup.py
bin/sshec2
sshec2/__init__.py
sshec2/sshec2.py
sshec2.egg-info/PKG-INFO
sshec2.egg-info/SOURCES.txt
sshec2.egg-info/dependency_links.txt
sshec2.egg-info/requires.txt
sshec2.egg-info/top_level.txt