Metadata-Version: 1.1
Name: sshec2
Version: 0.1.12
Summary: Utility for ssh login to EC2 instances.
Home-page: https://github.com/s-fujimoto/sshec2
Author: Shinji Fujimoto
Author-email: UNKNOWN
License: Apache License 2.0
Platform: UNKNOWN
Classifier: Intended Audience :: Developers
Classifier: Intended Audience :: System Administrators
Classifier: Natural Language :: English
Classifier: License :: OSI Approved :: Apache Software License
Classifier: Programming Language :: Python
Classifier: Programming Language :: Python :: 2.7
Classifier: Programming Language :: Python :: 3
Classifier: Programming Language :: Python :: 3.3
Classifier: Programming Language :: Python :: 3.4
Classifier: Programming Language :: Python :: 3.5
Classifier: Programming Language :: Python :: 3.6
